access_timer_middleware/__init__.py
access_timer_middleware/admin.py
access_timer_middleware/apps.py
access_timer_middleware/exceptions.py
access_timer_middleware/middleware.py
access_timer_middleware/models.py
access_timer_middleware/signals.py
access_timer_middleware/tests.py
access_timer_middleware/views.py
access_timer_middleware/migrations/0001_initial.py
access_timer_middleware/migrations/__init__.py
django_access_timer_middleware-1.4.dist-info/LICENSE
django_access_timer_middleware-1.4.dist-info/METADATA
django_access_timer_middleware-1.4.dist-info/WHEEL
django_access_timer_middleware-1.4.dist-info/top_level.txt
django_access_timer_middleware-1.4.dist-info/RECORD
