Metadata-Version: 2.1
Name: django-access-timer-middleware
Version: 1.4
Summary: Access timer middleware is a middleware which allow to control access to some paths, like /api/, /admin/ and what you want!
Author-email: pavelbeard <heavycream9090@icloud.com>
Project-URL: Homepage, https://github.com/pavelbeard/django-access-timer-middleware
Project-URL: Issues, https://github.com/pavelbeard/django-access-timer-middleware/issues
Classifier: Programming Language :: Python :: 3
Classifier: License :: OSI Approved :: MIT License
Classifier: Operating System :: OS Independent
Requires-Python: >=3.8
License-File: LICENSE
